thothclient/__init__.py
thothclient-0.1.dist-info/LICENSE.md
thothclient-0.1.dist-info/METADATA
thothclient-0.1.dist-info/WHEEL
thothclient-0.1.dist-info/top_level.txt
thothclient-0.1.dist-info/RECORD
