Metadata-Version: 2.1
Name: thothclient
Version: 0.1
Summary: User client for thothbackup
Home-page: https://github.com/zyradyl/thothclient
Author: Zyradyl
Author-email: nmspencer89@outlook.com
License: ISC
Platform: UNKNOWN
Classifier: Programming Language :: Python :: 3
Classifier: License :: OSI Approved :: ISC License (ISCL)
Classifier: Operating System :: OS Independent
